country_call
