Metadata-Version: 2.1
Name: country-call
Version: 1.0.1.1
Summary: Introducing a powerful and easy-to-use Python library for country detection from ambiguous text, designed for developers and data scientists alike.
Author: Md Shamim Hasan, Kazi Arman Rahat, Mukitul Islam, Anik Roy
Author-email: shihab18015@gmail.com
Keywords: country,origin,nlp
Classifier: Intended Audience :: Education
Classifier: License :: OSI Approved :: MIT License
Classifier: Programming Language :: Python :: 3
License-File: Licence.txt
